g2papi/__init__.py
g2papi/api.py
g2papi/cli.py
g2papi-1.0.4.dist-info/LICENSE
g2papi-1.0.4.dist-info/METADATA
g2papi-1.0.4.dist-info/WHEEL
g2papi-1.0.4.dist-info/entry_points.txt
g2papi-1.0.4.dist-info/top_level.txt
g2papi-1.0.4.dist-info/RECORD
