Metadata-Version: 2.1
Name: g2papi
Version: 1.0.4
Summary: A python client and CLI for easy access to G2P portal APIs
Author: Jordan Safer
Author-email: genomics2proteins@gmail.com
License: UNKNOWN
Project-URL: GitHub, https://www.github.com/broadinstitute/g2papi
Project-URL: G2P portal, https://g2p.broadinstitute.org
Platform: UNKNOWN
License-File: LICENSE
Requires-Dist: requests
Requires-Dist: pandas
